bootstrap.py
buildout.cfg
setup.py
src/keas/__init__.py
src/keas.pbstate.egg-info/PKG-INFO
src/keas.pbstate.egg-info/SOURCES.txt
src/keas.pbstate.egg-info/dependency_links.txt
src/keas.pbstate.egg-info/namespace_packages.txt
src/keas.pbstate.egg-info/requires.txt
src/keas.pbstate.egg-info/top_level.txt
src/keas/pbstate/README.txt
src/keas/pbstate/__init__.py
src/keas/pbstate/meta.py
src/keas/pbstate/state.py
src/keas/pbstate/testclasses.proto
src/keas/pbstate/testclasses_pb2.py
src/keas/pbstate/tests.py