Metadata-Version: 1.0
Name: keas.pbstate
Version: 0.1
Summary: An object database foundation based on Google's Protocol Buffers
Home-page: UNKNOWN
Author: Shane Hathaway and the Zope Community
Author-email: zope-dev@zope.org
License: ZPL 2.1
Platform: UNKNOWN
